dysh/__init__.py
dysh/__main__.py
dysh/ascii.py
dysh/log.py
dysh/config/__init__.py
dysh/config/core.py
dysh/config/tests/test_config_core.py
dysh/coordinates/__init__.py
dysh/coordinates/core.py
dysh/coordinates/tests/test_coordinates_core.py
dysh/data/GBTIDL_RRF_w_Kup.csv.gz
dysh/data/calibrators.json
dysh/data/gaincorrection.tab
dysh/data/gbtlines.csv.gz
dysh/data/gbtrecomb.csv.gz
dysh/fits/__init__.py
dysh/fits/core.py
dysh/fits/gb20mfitsload.py
dysh/fits/gbtfitsload.py
dysh/fits/sdfitsload.py
dysh/fits/tests/test_gb20mfitsload.py
dysh/fits/tests/test_gbtfitsload.py
dysh/fits/tests/test_sdfitsload.py
dysh/lab_templates/dysh/default.ipynb
dysh/line/__init__.py
dysh/line/search.py
dysh/line/tests/test_search.py
dysh/plot/__init__.py
dysh/plot/core.py
dysh/plot/scanplot.py
dysh/plot/specplot.py
dysh/plot/vegasplot.py
dysh/plot/tests/test_plot_reuse.py
dysh/plot/tests/test_specplot.py
dysh/shell/__init__.py
dysh/shell/jp_app_launcher_config.yaml
dysh/shell/lab.py
dysh/shell/shell.py
dysh/shell/test_shell.py
dysh/spectra/__init__.py
dysh/spectra/core.py
dysh/spectra/scan.py
dysh/spectra/spectrum.py
dysh/spectra/tcal.py
dysh/spectra/vane.py
dysh/spectra/tests/conftest.py
dysh/spectra/tests/test_doppler_conventions.py
dysh/spectra/tests/test_doppler_frames.py
dysh/spectra/tests/test_scan.py
dysh/spectra/tests/test_spectra_core.py
dysh/spectra/tests/test_spectrum.py
dysh/spectra/tests/test_tcal.py
dysh/util/__init__.py
dysh/util/calibrator.py
dysh/util/core.py
dysh/util/docstring_manip.py
dysh/util/download.py
dysh/util/files.py
dysh/util/gaincorrection.py
dysh/util/selection.py
dysh/util/timers.py
dysh/util/weatherforecast.py
dysh/util/tests/test_calibrator.py
dysh/util/tests/test_docstring_manip.py
dysh/util/tests/test_download.py
dysh/util/tests/test_files.py
dysh/util/tests/test_gaincorrection.py
dysh/util/tests/test_selection.py
dysh/util/tests/test_timers.py
dysh/util/tests/test_util_core.py
dysh/util/tests/test_weatherforecast.py
dysh-0.11.5.dist-info/METADATA
dysh-0.11.5.dist-info/WHEEL
dysh-0.11.5.dist-info/entry_points.txt
dysh-0.11.5.dist-info/licenses/LICENSE
dysh-0.11.5.dist-info/RECORD
