Metadata-Version: 2.4
Name: dysh
Version: 0.11.5
Project-URL: Documentation, https://github.com/GreenBankObservatory/dysh#readme
Project-URL: Issues, https://github.com/GreenBankObservatory/dysh/issues
Project-URL: Source, https://github.com/GreenBankObservatory/dysh
Author: Victoria Catlett
Author-email: Marc Pound <mpound@umd.edu>, Peter Teuben <teuben@umd.edu>, Pedro Salas <psalas@nrao.edu>, Evan Smith <esmith@nrao.edu>, Thomas Chamberlin <tchamber@nrao.edu>
License: GNU GENERAL PUBLIC LICENSE
License-File: LICENSE
Classifier: Development Status :: 4 - Beta
Classifier: Programming Language :: Python
Classifier: Programming Language :: Python :: 3
Classifier: Programming Language :: Python :: Implementation :: CPython
Requires-Python: >=3.10
Requires-Dist: astropy>=6.1
Requires-Dist: astroquery
Requires-Dist: httpx
Requires-Dist: ipython
Requires-Dist: jplephem
Requires-Dist: matplotlib
Requires-Dist: numpy
Requires-Dist: pandas
Requires-Dist: platformdirs>=4.5.0
Requires-Dist: rich
Requires-Dist: scipy
Requires-Dist: specutils>=2
Requires-Dist: tenacity
Provides-Extra: all
Requires-Dist: ipympl; extra == 'all'
Requires-Dist: jupyter; extra == 'all'
Requires-Dist: jupyter-app-launcher>=0.3.1; extra == 'all'
Requires-Dist: jupyter-nbextensions-configurator>=0.6.4; extra == 'all'
Requires-Dist: jupyterlab; extra == 'all'
Requires-Dist: jupyterlab-lsp>=5.2.0; extra == 'all'
Requires-Dist: jupyterlab-templates>=0.5.3; extra == 'all'
Provides-Extra: nb
Requires-Dist: ipympl; extra == 'nb'
Requires-Dist: jupyter; extra == 'nb'
Requires-Dist: jupyter-app-launcher>=0.3.1; extra == 'nb'
Requires-Dist: jupyter-nbextensions-configurator>=0.6.4; extra == 'nb'
Requires-Dist: jupyterlab; extra == 'nb'
Requires-Dist: jupyterlab-lsp>=5.2.0; extra == 'nb'
Requires-Dist: jupyterlab-templates>=0.5.3; extra == 'nb'
